<?xml version='1.0' encoding='utf-8'?><m:page id='6ad9edfa-ed02-473c-a976-5006a6f8270e' xmlns='http://www.w3.org/1999/xhtml' title='Homepage' class='layout-atlas layout-atlas-responsive-default page-dashboard page-dashboard-actions' xmlns:m='http://schemas.mendix.com/forms/1.0'><m:layouts><m:layout path='Atlas_UI_Resources/Atlas_Default.layout.xml'></m:layout></m:layouts><m:arguments><m:argument parameterName='6cb33f58-e3e4-48f8-b16e-78bdaa93618c'><div data-mendix-id='2.MyFirstModule.Home_Web.container18' data-mendix-type='mxui.widget.ReactWidgetWrapper' data-mendix-props='"widgetTree":[{"$widgetId":"2.MyFirstModule.Home_Web.container18","widget":"Container","props":{"class":"mx-name-container18","renderMode":"div","onClick":null,"content":[{"$widgetId":"2.MyFirstModule.Home_Web.actionButton5","widget":"ActionButton","props":{"buttonId":"2.MyFirstModule.Home_Web.actionButton5","class":"mx-name-actionButton5","renderType":"button","buttonClass":"btn-default","caption":{"$type":"ExpressionProperty","expression":{"expr":{"type":"literal","value":"teac_log_in"},"args":{}}},"tooltip":{"$type":"TextProperty","value":""},"action":{"$type":"ActionProperty","action":{"type":"createObject","argMap":{},"config":{"entity":"MyFirstModule.Login_teacher","pageSettings":{"name":"MyFirstModule/teacher_logIn_page_2.page.xml","location":"content"}},"disabledDuringExecution":true},"abortOnServerValidation":true}}},{"$widgetId":"2.MyFirstModule.Home_Web.actionButton7","widget":"ActionButton","props":{"buttonId":"2.MyFirstModule.Home_Web.actionButton7","class":"mx-name-actionButton7","renderType":"button","buttonClass":"btn-default","caption":{"$type":"ExpressionProperty","expression":{"expr":{"type":"literal","value":"add_cpurse"},"args":{}}},"tooltip":{"$type":"TextProperty","value":""},"action":{"$type":"ActionProperty","action":{"type":"createObject","argMap":{},"config":{"entity":"MyFirstModule.course_upload","pageSettings":{"name":"MyFirstModule/add_course_2.page.xml","location":"content"}},"disabledDuringExecution":true},"abortOnServerValidation":true}}},{"$widgetId":"2.MyFirstModule.Home_Web.actionButton8","widget":"ActionButton","props":{"buttonId":"2.MyFirstModule.Home_Web.actionButton8","class":"mx-name-actionButton8","renderType":"button","buttonClass":"btn-default","caption":{"$type":"ExpressionProperty","expression":{"expr":{"type":"literal","value":"Button"},"args":{}}},"tooltip":{"$type":"TextProperty","value":""},"action":{"$type":"ActionProperty","action":{"type":"createObject","argMap":{},"config":{"entity":"MyFirstModule.course_upload","pageSettings":{"name":"MyFirstModule/add_2.page.xml","location":"modal","resizable":true}},"disabledDuringExecution":true},"abortOnServerValidation":true}}},{"$widgetId":"2.MyFirstModule.Home_Web.actionButton9","widget":"ActionButton","props":{"buttonId":"2.MyFirstModule.Home_Web.actionButton9","class":"mx-name-actionButton9","renderType":"button","buttonClass":"btn-default","caption":{"$type":"ExpressionProperty","expression":{"expr":{"type":"literal","value":"Button"},"args":{}}},"tooltip":{"$type":"TextProperty","value":""},"action":{"$type":"ActionProperty","action":{"type":"createObject","argMap":{},"config":{"entity":"MyFirstModule.course_upload","pageSettings":{"name":"MyFirstModule/show_video_2_2.page.xml","location":"content"}},"disabledDuringExecution":true},"abortOnServerValidation":true}}},{"$widgetId":"2.MyFirstModule.Home_Web.image1","widget":"Image","props":{"class":"mx-name-image1 heroheaderproduct-backgroundimage img-center","alternativeText":{"$type":"ExpressionProperty","expression":{"expr":{"type":"literal","value":"TEXT"},"args":{}}},"height":"50%","width":"200%","responsive":true,"source":{"$type":"StaticImageProperty","image":{"uri":"img/MyFirstModule$Images$ed_tech1553237040995.png?637520360569111426"}},"onClick":null}}],"ariaHidden":false}}],"listenTargets":[]'></div><div data-mendix-id='2.MyFirstModule.Home_Web.container27' data-mendix-type='mxui.widget.ReactWidgetWrapper' data-mendix-props='"widgetTree":[{"$widgetId":"2.MyFirstModule.Home_Web.container27","widget":"Container","props":{"class":"mx-name-container27 background-danger","renderMode":"div","onClick":null,"content":[{"$widgetId":"2.MyFirstModule.Home_Web.text1","widget":"Text","props":{"class":"mx-name-text1 text-inverse text-center d-block","style":{"color":"white"},"caption":{"$type":"ExpressionProperty","expression":{"expr":{"type":"literal","value":"ALL COURSES"},"args":{}}},"renderMode":"h2"}}],"ariaHidden":false}}],"listenTargets":[]'></div><div data-mendix-id='2.MyFirstModule.Home_Web.container14' data-mendix-type='mxui.widget.ReactWidgetWrapper' data-mendix-props='"widgetTree":[{"$widgetId":"2.MyFirstModule.Home_Web.container14","widget":"Container","props":{"class":"mx-name-container14","style":{"backgroundColor":"rgba(201, 76, 76, 0.3)"},"renderMode":"div","onClick":null,"content":[{"$widgetId":"2.MyFirstModule.Home_Web.text16","widget":"Text","props":{"class":"mx-name-text16 movingtext","style":{"color":"black"},"caption":{"$type":"ExpressionProperty","expression":{"expr":{"type":"literal","value":"“Learning to code is learning to create and innovate.”"},"args":{}}},"renderMode":"h3"}}],"ariaHidden":false}}],"listenTargets":[]'></div><div data-mendix-id='2.MyFirstModule.Home_Web.container1' data-mendix-type='mxui.widget.ReactWidgetWrapper' data-mendix-props='"widgetTree":[{"$widgetId":"2.MyFirstModule.Home_Web.container1","widget":"Container","props":{"class":"mx-name-container1","renderMode":"div","onClick":null,"content":[{"$widgetId":"2.MyFirstModule.Home_Web.layoutGrid1","widget":"Div","props":{"class":"mx-name-layoutGrid1 mx-layoutgrid mx-layoutgrid-fluid container-fluid","content":[{"$widgetId":"2.MyFirstModule.Home_Web.layoutGrid1$row0","widget":"Div","props":{"class":"row","content":[{"$widgetId":"2.MyFirstModule.Home_Web.layoutGrid1$row0$column0","widget":"Div","props":{"class":"col-lg col-md col","content":[{"$widgetId":"2.MyFirstModule.Home_Web.image5","widget":"Image","props":{"class":"mx-name-image5","alternativeText":{"$type":"ExpressionProperty","expression":{"expr":{"type":"literal","value":""},"args":{}}},"height":"43%","width":"100%","responsive":true,"source":{"$type":"StaticImageProperty","image":{"uri":"img/MyFirstModule$Images$phython_code_symbol_sur_portable_1600.png?637520360569111426"}},"onClick":null}},{"$widgetId":"2.MyFirstModule.Home_Web.container3","widget":"Container","props":{"class":"mx-name-container3","renderMode":"div","onClick":null,"content":[{"$widgetId":"2.MyFirstModule.Home_Web.container2","widget":"Container","props":{"class":"mx-name-container2","renderMode":"div","onClick":null,"content":[{"$widgetId":"2.MyFirstModule.Home_Web.text2","widget":"Text","props":{"class":"mx-name-text2 text-center d-block","style":{"color":"black"},"caption":{"$type":"ExpressionProperty","expression":{"expr":{"type":"literal","value":"PYTHON"},"args":{}}},"renderMode":"h3"}}],"ariaHidden":false}},{"$widgetId":"2.MyFirstModule.Home_Web.container10","widget":"Container","props":{"class":"mx-name-container10","renderMode":"div","onClick":null,"content":[{"$widgetId":"2.MyFirstModule.Home_Web.text6","widget":"Text","props":{"class":"mx-name-text6","style":{"color":"black"},"caption":{"$type":"ExpressionProperty","expression":{"expr":{"type":"literal","value":"Learn Python, one of today&apos;s most in-demand programming languages on-the-go!"},"args":{}}},"renderMode":"h4"}}],"ariaHidden":false}}],"ariaHidden":false}}]}},{"$widgetId":"2.MyFirstModule.Home_Web.layoutGrid1$row0$column1","widget":"Div","props":{"class":"col-lg col-md col","content":[{"$widgetId":"2.MyFirstModule.Home_Web.image6","widget":"Image","props":{"class":"mx-name-image6","alternativeText":{"$type":"ExpressionProperty","expression":{"expr":{"type":"literal","value":""},"args":{}}},"responsive":true,"source":{"$type":"StaticImageProperty","image":{"uri":"img/MyFirstModule$Images$c_programming.jpg?637520360569111426"}},"onClick":null}},{"$widgetId":"2.MyFirstModule.Home_Web.container7","widget":"Container","props":{"class":"mx-name-container7","renderMode":"div","onClick":null,"content":[{"$widgetId":"2.MyFirstModule.Home_Web.container6","widget":"Container","props":{"class":"mx-name-container6","renderMode":"div","onClick":null,"content":[{"$widgetId":"2.MyFirstModule.Home_Web.text3","widget":"Text","props":{"class":"mx-name-text3 text-center d-block","style":{"color":"black"},"caption":{"$type":"ExpressionProperty","expression":{"expr":{"type":"literal","value":"C++"},"args":{}}},"renderMode":"h3"}}],"ariaHidden":false}},{"$widgetId":"2.MyFirstModule.Home_Web.container11","widget":"Container","props":{"class":"mx-name-container11","renderMode":"div","onClick":null,"content":[{"$widgetId":"2.MyFirstModule.Home_Web.text7","widget":"Text","props":{"class":"mx-name-text7","style":{"color":"black"},"caption":{"$type":"ExpressionProperty","expression":{"expr":{"type":"literal","value":"Our C++ tutorial covers basic concepts, data types, arrays, pointers, conditional statements, loops, functions, classes and objects."},"args":{}}},"renderMode":"h4"}}],"ariaHidden":false}}],"ariaHidden":false}}]}},{"$widgetId":"2.MyFirstModule.Home_Web.layoutGrid1$row0$column2","widget":"Div","props":{"class":"col-lg col-md col","content":[{"$widgetId":"2.MyFirstModule.Home_Web.image4","widget":"Image","props":{"class":"mx-name-image4","alternativeText":{"$type":"ExpressionProperty","expression":{"expr":{"type":"literal","value":""},"args":{}}},"responsive":true,"source":{"$type":"StaticImageProperty","image":{"uri":"img/MyFirstModule$Images$_1571114082_power_bi_new_3_story.jpg?637520360569111426"}},"onClick":null}},{"$widgetId":"2.MyFirstModule.Home_Web.container5","widget":"Container","props":{"class":"mx-name-container5","renderMode":"div","onClick":null,"content":[{"$widgetId":"2.MyFirstModule.Home_Web.container4","widget":"Container","props":{"class":"mx-name-container4","renderMode":"div","onClick":null,"content":[{"$widgetId":"2.MyFirstModule.Home_Web.text4","widget":"Text","props":{"class":"mx-name-text4 text-center d-block","style":{"color":"black"},"caption":{"$type":"ExpressionProperty","expression":{"expr":{"type":"literal","value":"POWER BI"},"args":{}}},"renderMode":"h3"}}],"ariaHidden":false}},{"$widgetId":"2.MyFirstModule.Home_Web.container12","widget":"Container","props":{"class":"mx-name-container12","renderMode":"div","onClick":null,"content":[{"$widgetId":"2.MyFirstModule.Home_Web.text8","widget":"Text","props":{"class":"mx-name-text8","style":{"color":"black"},"caption":{"$type":"ExpressionProperty","expression":{"expr":{"type":"literal","value":"The BI stands for “business intelligence,” and the tool gives non-technical users all the resources they need to aggregate, visualize, analyze, and share data."},"args":{}}},"renderMode":"h4"}}],"ariaHidden":false}}],"ariaHidden":false}}]}},{"$widgetId":"2.MyFirstModule.Home_Web.layoutGrid1$row0$column3","widget":"Div","props":{"class":"col-lg col-md col","content":[{"$widgetId":"2.MyFirstModule.Home_Web.image3","widget":"Image","props":{"class":"mx-name-image3","alternativeText":{"$type":"ExpressionProperty","expression":{"expr":{"type":"literal","value":""},"args":{}}},"responsive":true,"source":{"$type":"StaticImageProperty","image":{"uri":"img/MyFirstModule$Images$ja1.jpg?637520360569111426"}},"onClick":null}},{"$widgetId":"2.MyFirstModule.Home_Web.container9","widget":"Container","props":{"class":"mx-name-container9","renderMode":"div","onClick":null,"content":[{"$widgetId":"2.MyFirstModule.Home_Web.container8","widget":"Container","props":{"class":"mx-name-container8","renderMode":"div","onClick":null,"content":[{"$widgetId":"2.MyFirstModule.Home_Web.text5","widget":"Text","props":{"class":"mx-name-text5 text-center d-block","style":{"color":"black"},"caption":{"$type":"ExpressionProperty","expression":{"expr":{"type":"literal","value":"JAVA"},"args":{}}},"renderMode":"h3"}}],"ariaHidden":false}},{"$widgetId":"2.MyFirstModule.Home_Web.container13","widget":"Container","props":{"class":"mx-name-container13","renderMode":"div","onClick":null,"content":[{"$widgetId":"2.MyFirstModule.Home_Web.text9","widget":"Text","props":{"class":"mx-name-text9","style":{"color":"black"},"caption":{"$type":"ExpressionProperty","expression":{"expr":{"type":"literal","value":"With our interactive Java course, you’ll learn object-oriented Java programming and have the ability to write clear and valid code in almost no time at all."},"args":{}}},"renderMode":"h4"}}],"ariaHidden":false}}],"ariaHidden":false}}]}}]}}]}},{"$widgetId":"2.MyFirstModule.Home_Web.container17","widget":"Container","props":{"class":"mx-name-container17","renderMode":"div","onClick":null,"content":[{"$widgetId":"2.MyFirstModule.Home_Web.container16","widget":"Container","props":{"class":"mx-name-container16","renderMode":"div","onClick":null,"content":[{"$widgetId":"2.MyFirstModule.Home_Web.actionButton4","widget":"ActionButton","props":{"buttonId":"2.MyFirstModule.Home_Web.actionButton4","class":"mx-name-actionButton4 btn-bordered btn-block btn-lg","style":{"color":"blue"},"renderType":"button","buttonClass":"btn-inverse","caption":{"$type":"ExpressionProperty","expression":{"expr":{"type":"literal","value":"VIEW ALL COURSES -------&gt;"},"args":{}}},"tooltip":{"$type":"TextProperty","value":""},"action":{"$type":"ActionProperty","action":{"type":"openPage","argMap":{},"config":{"name":"MyFirstModule/All_courses.page.xml","location":"content"},"disabledDuringExecution":true},"abortOnServerValidation":true}}}],"ariaHidden":false}}],"ariaHidden":false}},{"$widgetId":"2.MyFirstModule.Home_Web.container26","widget":"Container","props":{"class":"mx-name-container26 background-danger","renderMode":"div","onClick":null,"content":[{"$widgetId":"2.MyFirstModule.Home_Web.text14","widget":"Text","props":{"class":"mx-name-text14 text-center d-block text-inverse","style":{"color":"white"},"caption":{"$type":"ExpressionProperty","expression":{"expr":{"type":"literal","value":"TEACHING SECTION"},"args":{}}},"renderMode":"h2"}}],"ariaHidden":false}},{"$widgetId":"2.MyFirstModule.Home_Web.container29","widget":"Container","props":{"class":"mx-name-container29 background1","renderMode":"div","onClick":null,"content":[{"$widgetId":"2.MyFirstModule.Home_Web.layoutGrid4","widget":"Div","props":{"class":"mx-name-layoutGrid4 mx-layoutgrid mx-layoutgrid-fluid container-fluid","content":[{"$widgetId":"2.MyFirstModule.Home_Web.layoutGrid4$row0","widget":"Div","props":{"class":"row","content":[{"$widgetId":"2.MyFirstModule.Home_Web.layoutGrid4$row0$column0","widget":"Div","props":{"class":"col-lg col-md col","content":[{"$widgetId":"2.MyFirstModule.Home_Web.container23","widget":"Container","props":{"class":"mx-name-container23","renderMode":"div","onClick":null,"content":[{"$widgetId":"2.MyFirstModule.Home_Web.image10","widget":"Image","props":{"class":"mx-name-image10","alternativeText":{"$type":"ExpressionProperty","expression":{"expr":{"type":"literal","value":""},"args":{}}},"height":"90%","width":"100%","responsive":true,"source":{"$type":"StaticImageProperty","image":{"uri":"img/MyFirstModule$Images$_20mm_make_themselves_more_visible_600x410.jpg?637520360569111426"}},"onClick":null}}],"ariaHidden":false}}]}},{"$widgetId":"2.MyFirstModule.Home_Web.layoutGrid4$row0$column1","widget":"Div","props":{"class":"col-lg col-md col","content":[{"$widgetId":"2.MyFirstModule.Home_Web.container24","widget":"Container","props":{"class":"mx-name-container24 spacing-outer-right-medium spacing-outer-top","renderMode":"div","onClick":null,"content":[{"$widgetId":"2.MyFirstModule.Home_Web.text12","widget":"Text","props":{"class":"mx-name-text12 spacing-outer-top text-uppercase","style":{"color":"white"},"caption":{"$type":"ExpressionProperty","expression":{"expr":{"type":"literal","value":"Teach The World Online"},"args":{}}},"renderMode":"h3"}},{"$widgetId":"2.MyFirstModule.Home_Web.text13","widget":"Text","props":{"class":"mx-name-text13","style":{"color":"green","fontFamily":"Impact"},"caption":{"$type":"ExpressionProperty","expression":{"expr":{"type":"literal","value":"\" Education is the most powerfull weapon which you can use to change the world \""},"args":{}}},"renderMode":"h2"}}],"ariaHidden":false}},{"$widgetId":"2.MyFirstModule.Home_Web.container25","widget":"Container","props":{"class":"mx-name-container25","renderMode":"div","onClick":null,"content":[{"$widgetId":"2.MyFirstModule.Home_Web.actionButton3","widget":"ActionButton","props":{"buttonId":"2.MyFirstModule.Home_Web.actionButton3","class":"mx-name-actionButton3 spacing-outer-top-large spacing-outer-left-medium","renderType":"button","buttonClass":"btn-primary","caption":{"$type":"ExpressionProperty","expression":{"expr":{"type":"literal","value":"INSTRUCTOR  SECTION"},"args":{}}},"tooltip":{"$type":"TextProperty","value":""},"icon":{"$type":"IconProperty","icon":{"type":"glyph","iconClass":"glyphicon-star"}},"action":{"$type":"ActionProperty","action":{"type":"openPage","argMap":{},"config":{"name":"MyFirstModule/Teacher_profile.page.xml","location":"content"},"disabledDuringExecution":true},"abortOnServerValidation":true}}}],"ariaHidden":false}}]}}]}}]}}],"ariaHidden":false}},{"$widgetId":"2.MyFirstModule.Home_Web.container28","widget":"Container","props":{"class":"mx-name-container28 row-center background-primary","renderMode":"div","onClick":null,"content":[{"$widgetId":"2.MyFirstModule.Home_Web.text15","widget":"Text","props":{"class":"mx-name-text15 spacing-outer-bottom-none text-semibold","style":{"color":"white"},"caption":{"$type":"ExpressionProperty","expression":{"expr":{"type":"literal","value":"\"NEVER STOP LEARNING AS LIFE NEVER STOP TEACHING\""},"args":{}}},"renderMode":"h2"}}],"ariaHidden":false}},{"$widgetId":"2.MyFirstModule.Home_Web.container22","widget":"Container","props":{"class":"mx-name-container22 img4 background-secondary","renderMode":"div","onClick":null,"content":[{"$widgetId":"2.MyFirstModule.Home_Web.layoutGrid3","widget":"Div","props":{"class":"mx-name-layoutGrid3 mx-layoutgrid mx-layoutgrid-fluid container-fluid","style":{"background":"rgba(0, 128, 0, 0.1)"},"content":[{"$widgetId":"2.MyFirstModule.Home_Web.layoutGrid3$row0","widget":"Div","props":{"class":"row","content":[{"$widgetId":"2.MyFirstModule.Home_Web.layoutGrid3$row0$column0","widget":"Div","props":{"class":"col-lg col-md col","content":[{"$widgetId":"2.MyFirstModule.Home_Web.container19","widget":"Container","props":{"class":"mx-name-container19 img4 background-secondary","renderMode":"footer","onClick":null,"content":[{"$widgetId":"2.MyFirstModule.Home_Web.text10","widget":"Text","props":{"class":"mx-name-text10","style":{"background":"rgba(0, 128, 0, 0.1)"},"caption":{"$type":"ExpressionProperty","expression":{"expr":{"type":"literal","value":"Online Reading App\r\n\r\nE-State,Hub\r\nBhubaneswar, Odisha 751014"},"args":{}}},"renderMode":"h5"}}],"ariaHidden":false}},{"$widgetId":"2.MyFirstModule.Home_Web.container20","widget":"Container","props":{"class":"mx-name-container20","renderMode":"footer","onClick":null,"content":[{"$widgetId":"2.MyFirstModule.Home_Web.actionButton1","widget":"ActionButton","props":{"buttonId":"2.MyFirstModule.Home_Web.actionButton1","class":"mx-name-actionButton1 spacing-outer-left","renderType":"button","buttonClass":"btn-inverse","caption":{"$type":"ExpressionProperty","expression":{"expr":{"type":"literal","value":"About Us"},"args":{}}},"tooltip":{"$type":"TextProperty","value":""},"action":{"$type":"ActionProperty","action":{"type":"openPage","argMap":{},"config":{"name":"MyFirstModule/About_Us.page.xml","location":"content"},"disabledDuringExecution":true},"abortOnServerValidation":true}}},{"$widgetId":"2.MyFirstModule.Home_Web.actionButton2","widget":"ActionButton","props":{"buttonId":"2.MyFirstModule.Home_Web.actionButton2","class":"mx-name-actionButton2 spacing-outer-right-none spacing-outer-left","renderType":"button","buttonClass":"btn-inverse","caption":{"$type":"ExpressionProperty","expression":{"expr":{"type":"literal","value":"T&amp;C"},"args":{}}},"tooltip":{"$type":"TextProperty","value":""},"action":{"$type":"ActionProperty","action":{"type":"openPage","argMap":{},"config":{"name":"MyFirstModule/Term_Condition.page.xml","location":"content"},"disabledDuringExecution":true},"abortOnServerValidation":true}}}],"ariaHidden":false}}]}},{"$widgetId":"2.MyFirstModule.Home_Web.layoutGrid3$row0$column1","widget":"Div","props":{"class":"col-lg col-md col","content":[{"$widgetId":"2.MyFirstModule.Home_Web.container21","widget":"Container","props":{"class":"mx-name-container21","renderMode":"footer","onClick":null,"content":[{"$widgetId":"2.MyFirstModule.Home_Web.text11","widget":"Text","props":{"class":"mx-name-text11","caption":{"$type":"ExpressionProperty","expression":{"expr":{"type":"literal","value":"Toll Free Number\r\n1800-111-334-070\r\n\r\nGeneral Queries:\r\nonline@reading.com / app@reading.com\r\n\r\n\r\nFeel free to send us your queries regarding products,service or to become our channel partner.Complains are welcome as well, we take them as a note for improvement and we endeavour to answer all enquires shortly on business days."},"args":{}}},"renderMode":"h5"}}],"ariaHidden":false}}]}}]}}]}}],"ariaHidden":false}}],"ariaHidden":false}}],"listenTargets":[]'></div></m:argument></m:arguments></m:page>